COPYING
wechat_extractor/__init__.py
wechat_extractor/__main__.py
wechat_extractor/commands/__init__.py
wechat_extractor-0.1.0.dist-info/COPYING
wechat_extractor-0.1.0.dist-info/METADATA
wechat_extractor-0.1.0.dist-info/WHEEL
wechat_extractor-0.1.0.dist-info/entry_points.txt
wechat_extractor-0.1.0.dist-info/RECORD
